{
  "version": "3.1.1",
  "flags": {},
  "shapes": [
    {
      "label": "old",
      "score": 0.8482752442359924,
      "points": [
        [
          1201.4250183105469,
          646.3213348388672
        ],
        [
          1223.7096977233887,
          646.3213348388672
        ],
        [
          1223.7096977233887,
          668.9332866668701
        ],
        [
          1201.4250183105469,
          668.9332866668701
        ]
      ],
      "group_id": null,
      "description": null,
      "difficult": false,
      "shape_type": "rectangle",
      "flags": {},
      "attributes": {},
      "kie_linking": []
    },
    {
      "label": "old",
      "score": 0.6831375360488892,
      "points": [
        [
          1202.3394298553467,
          727.0084714889526
        ],
        [
          1227.2153854370117,
          727.0084714889526
        ],
        [
          1227.2153854370117,
          750.9371995925903
        ],
        [
          1202.3394298553467,
          750.9371995925903
        ]
      ],
      "group_id": null,
      "description": null,
      "difficult": false,
      "shape_type": "rectangle",
      "flags": {},
      "attributes": {},
      "kie_linking": []
    },
    {
      "label": "3+",
      "score": 0.6514602899551392,
      "points": [
        [
          392.67383098602295,
          103.03338289260864
        ],
        [
          430.12109756469727,
          103.03338289260864
        ],
        [
          430.12109756469727,
          139.02141213417053
        ],
        [
          392.67383098602295,
          139.02141213417053
        ]
      ],
      "group_id": null,
      "description": null,
      "difficult": false,
      "shape_type": "rectangle",
      "flags": {},
      "attributes": {},
      "kie_linking": []
    },
    {
      "label": "3",
      "score": 0.6265478134155273,
      "points": [
        [
          909.6553039550781,
          442.21968173980713
        ],
        [
          943.2112216949463,
          442.21968173980713
        ],
        [
          943.2112216949463,
          474.96599197387695
        ],
        [
          909.6553039550781,
          474.96599197387695
        ]
      ],
      "group_id": null,
      "description": null,
      "difficult": false,
      "shape_type": "rectangle",
      "flags": {},
      "attributes": {},
      "kie_linking": []
    },
    {
      "label": "3+",
      "score": 0.6230234503746033,
      "points": [
        [
          305.2525544166565,
          178.95718336105347
        ],
        [
          335.0416612625122,
          178.95718336105347
        ],
        [
          335.0416612625122,
          211.15796566009521
        ],
        [
          305.2525544166565,
          211.15796566009521
        ]
      ],
      "group_id": null,
      "description": null,
      "difficult": false,
      "shape_type": "rectangle",
      "flags": {},
      "attributes": {},
      "kie_linking": []
    },
    {
      "label": "old",
      "score": 0.6197333335876465,
      "points": [
        [
          1200.6111979484558,
          896.9542074203491
        ],
        [
          1223.7613606452942,
          896.9542074203491
        ],
        [
          1223.7613606452942,
          922.376503944397
        ],
        [
          1200.6111979484558,
          922.376503944397
        ]
      ],
      "group_id": null,
      "description": null,
      "difficult": false,
      "shape_type": "rectangle",
      "flags": {},
      "attributes": {},
      "kie_linking": []
    },
    {
      "label": "2",
      "score": 0.6110447645187378,
      "points": [
        [
          793.5425543785095,
          756.5544891357422
        ],
        [
          816.1546540260315,
          756.5544891357422
        ],
        [
          816.1546540260315,
          780.3206157684326
        ],
        [
          793.5425543785095,
          780.3206157684326
        ]
      ],
      "group_id": null,
      "description": null,
      "difficult": false,
      "shape_type": "rectangle",
      "flags": {},
      "attributes": {},
      "kie_linking": []
    },
    {
      "label": "3+",
      "score": 0.6097531318664551,
      "points": [
        [
          360.20904302597046,
          148.89958083629608
        ],
        [
          385.47878980636597,
          148.89958083629608
        ],
        [
          385.47878980636597,
          181.69049561023712
        ],
        [
          360.20904302597046,
          181.69049561023712
        ]
      ],
      "group_id": null,
      "description": null,
      "difficult": false,
      "shape_type": "rectangle",
      "flags": {},
      "attributes": {},
      "kie_linking": []
    },
    {
      "label": "old",
      "score": 0.5896457433700562,
      "points": [
        [
          890.6749820709229,
          316.4519155025482
        ],
        [
          917.6437664031982,
          316.4519155025482
        ],
        [
          917.6437664031982,
          344.8063600063324
        ],
        [
          890.6749820709229,
          344.8063600063324
        ]
      ],
      "group_id": null,
      "description": null,
      "difficult": false,
      "shape_type": "rectangle",
      "flags": {},
      "attributes": {},
      "kie_linking": []
    },
    {
      "label": "2",
      "score": 0.5873568058013916,
      "points": [
        [
          735.1545095443726,
          637.7764797210693
        ],
        [
          758.1711912155151,
          637.7764797210693
        ],
        [
          758.1711912155151,
          658.8002586364746
        ],
        [
          735.1545095443726,
          658.8002586364746
        ]
      ],
      "group_id": null,
      "description": null,
      "difficult": false,
      "shape_type": "rectangle",
      "flags": {},
      "attributes": {},
      "kie_linking": []
    },
    {
      "label": "old",
      "score": 0.5617401003837585,
      "points": [
        [
          1090.3822565078735,
          861.9660663604736
        ],
        [
          1114.7340440750122,
          861.9660663604736
        ],
        [
          1114.7340440750122,
          886.5423917770386
        ],
        [
          1090.3822565078735,
          886.5423917770386
        ]
      ],
      "group_id": null,
      "description": null,
      "difficult": false,
      "shape_type": "rectangle",
      "flags": {},
      "attributes": {},
      "kie_linking": []
    },
    {
      "label": "3",
      "score": 0.545663058757782,
      "points": [
        [
          438.5792565345764,
          459.2119789123535
        ],
        [
          465.5548405647278,
          459.2119789123535
        ],
        [
          465.5548405647278,
          486.60027503967285
        ],
        [
          438.5792565345764,
          486.60027503967285
        ]
      ],
      "group_id": null,
      "description": null,
      "difficult": false,
      "shape_type": "rectangle",
      "flags": {},
      "attributes": {},
      "kie_linking": []
    },
    {
      "label": "3",
      "score": 0.5402050018310547,
      "points": [
        [
          468.5168480873108,
          424.02295112609863
        ],
        [
          494.60773229599,
          424.02295112609863
        ],
        [
          494.60773229599,
          450.77857971191406
        ],
        [
          468.5168480873108,
          450.77857971191406
        ]
      ],
      "group_id": null,
      "description": null,
      "difficult": false,
      "shape_type": "rectangle",
      "flags": {},
      "attributes": {},
      "kie_linking": []
    },
    {
      "label": "2",
      "score": 0.5301105976104736,
      "points": [
        [
          793.9537143707275,
          573.696939945221
        ],
        [
          819.2283391952515,
          573.696939945221
        ],
        [
          819.2283391952515,
          597.9251503944397
        ],
        [
          793.9537143707275,
          597.9251503944397
        ]
      ],
      "group_id": null,
      "description": null,
      "difficult": false,
      "shape_type": "rectangle",
      "flags": {},
      "attributes": {},
      "kie_linking": []
    },
    {
      "label": "2",
      "score": 0.520305871963501,
      "points": [
        [
          802.4138689041138,
          726.3262844085693
        ],
        [
          824.1817712783813,
          726.3262844085693
        ],
        [
          824.1817712783813,
          748.7074899673462
        ],
        [
          802.4138689041138,
          748.7074899673462
        ]
      ],
      "group_id": null,
      "description": null,
      "difficult": false,
      "shape_type": "rectangle",
      "flags": {},
      "attributes": {},
      "kie_linking": []
    },
    {
      "label": "2",
      "score": 0.5159047842025757,
      "points": [
        [
          723.7730717658997,
          615.0388073921204
        ],
        [
          745.7437825202942,
          615.0388073921204
        ],
        [
          745.7437825202942,
          635.74373960495
        ],
        [
          723.7730717658997,
          635.74373960495
        ]
      ],
      "group_id": null,
      "description": null,
      "difficult": false,
      "shape_type": "rectangle",
      "flags": {},
      "attributes": {},
      "kie_linking": []
    },
    {
      "label": "old",
      "score": 0.5157013535499573,
      "points": [
        [
          1110.2307224273682,
          668.9193916320801
        ],
        [
          1142.7678680419922,
          668.9193916320801
        ],
        [
          1142.7678680419922,
          695.0130844116211
        ],
        [
          1110.2307224273682,
          695.0130844116211
        ]
      ],
      "group_id": null,
      "description": null,
      "difficult": false,
      "shape_type": "rectangle",
      "flags": {},
      "attributes": {},
      "kie_linking": []
    },
    {
      "label": "2",
      "score": 0.5072224140167236,
      "points": [
        [
          649.8324918746948,
          569.0214455127716
        ],
        [
          675.8602571487427,
          569.0214455127716
        ],
        [
          675.8602571487427,
          592.3581564426422
        ],
        [
          649.8324918746948,
          592.3581564426422
        ]
      ],
      "group_id": null,
      "description": null,
      "difficult": false,
      "shape_type": "rectangle",
      "flags": {},
      "attributes": {},
      "kie_linking": []
    },
    {
      "label": "old",
      "score": 0.49728360772132874,
      "points": [
        [
          1076.3884782791138,
          893.0227994918823
        ],
        [
          1103.1115865707397,
          893.0227994918823
        ],
        [
          1103.1115865707397,
          915.7722234725952
        ],
        [
          1076.3884782791138,
          915.7722234725952
        ]
      ],
      "group_id": null,
      "description": null,
      "difficult": false,
      "shape_type": "rectangle",
      "flags": {},
      "attributes": {},
      "kie_linking": []
    },
    {
      "label": "3",
      "score": 0.49072742462158203,
      "points": [
        [
          71.73827230930328,
          603.5292100906372
        ],
        [
          104.70405757427216,
          603.5292100906372
        ],
        [
          104.70405757427216,
          635.3915596008301
        ],
        [
          71.73827230930328,
          635.3915596008301
        ]
      ],
      "group_id": null,
      "description": null,
      "difficult": false,
      "shape_type": "rectangle",
      "flags": {},
      "attributes": {},
      "kie_linking": []
    },
    {
      "label": "2",
      "score": 0.4877232015132904,
      "points": [
        [
          877.8047060966492,
          676.5066719055176
        ],
        [
          900.038092136383,
          676.5066719055176
        ],
        [
          900.038092136383,
          699.6858072280884
        ],
        [
          877.8047060966492,
          699.6858072280884
        ]
      ],
      "group_id": null,
      "description": null,
      "difficult": false,
      "shape_type": "rectangle",
      "flags": {},
      "attributes": {},
      "kie_linking": []
    },
    {
      "label": "old",
      "score": 0.48269009590148926,
      "points": [
        [
          869.3177962303162,
          351.2469673156738
        ],
        [
          896.1386132240295,
          351.2469673156738
        ],
        [
          896.1386132240295,
          382.20953941345215
        ],
        [
          869.3177962303162,
          382.20953941345215
        ]
      ],
      "group_id": null,
      "description": null,
      "difficult": false,
      "shape_type": "rectangle",
      "flags": {},
      "attributes": {},
      "kie_linking": []
    },
    {
      "label": "2+",
      "score": 0.4796741008758545,
      "points": [
        [
          389.49334621429443,
          513.0641078948975
        ],
        [
          415.7124638557434,
          513.0641078948975
        ],
        [
          415.7124638557434,
          538.8025903701782
        ],
        [
          389.49334621429443,
          538.8025903701782
        ]
      ],
      "group_id": null,
      "description": null,
      "difficult": false,
      "shape_type": "rectangle",
      "flags": {},
      "attributes": {},
      "kie_linking": []
    },
    {
      "label": "3+",
      "score": 0.46376940608024597,
      "points": [
        [
          301.12013041973114,
          134.57300543785095
        ],
        [
          327.5867533683777,
          134.57300543785095
        ],
        [
          327.5867533683777,
          168.19074869155884
        ],
        [
          301.12013041973114,
          168.19074869155884
        ]
      ],
      "group_id": null,
      "description": null,
      "difficult": false,
      "shape_type": "rectangle",
      "flags": {},
      "attributes": {},
      "kie_linking": []
    },
    {
      "label": "2",
      "score": 0.46318694949150085,
      "points": [
        [
          664.3290042877197,
          532.6020789146423
        ],
        [
          691.0775375366211,
          532.6020789146423
        ],
        [
          691.0775375366211,
          558.9104056358337
        ],
        [
          664.3290042877197,
          558.9104056358337
        ]
      ],
      "group_id": null,
      "description": null,
      "difficult": false,
      "shape_type": "rectangle",
      "flags": {},
      "attributes": {},
      "kie_linking": []
    },
    {
      "label": "2",
      "score": 0.45336300134658813,
      "points": [
        [
          794.973669052124,
          602.0442152023315
        ],
        [
          818.3232402801514,
          602.0442152023315
        ],
        [
          818.3232402801514,
          626.0211324691772
        ],
        [
          794.973669052124,
          626.0211324691772
        ]
      ],
      "group_id": null,
      "description": null,
      "difficult": false,
      "shape_type": "rectangle",
      "flags": {},
      "attributes": {},
      "kie_linking": []
    },
    {
      "label": "2",
      "score": 0.44427019357681274,
      "points": [
        [
          628.9766359329224,
          514.9452221393585
        ],
        [
          653.8620519638062,
          514.9452221393585
        ],
        [
          653.8620519638062,
          539.3646371364594
        ],
        [
          628.9766359329224,
          539.3646371364594
        ]
      ],
      "group_id": null,
      "description": null,
      "difficult": false,
      "shape_type": "rectangle",
      "flags": {},
      "attributes": {},
      "kie_linking": []
    },
    {
      "label": "2",
      "score": 0.4442249834537506,
      "points": [
        [
          739.8353624343872,
          591.463885307312
        ],
        [
          761.170449256897,
          591.463885307312
        ],
        [
          761.170449256897,
          615.3336334228516
        ],
        [
          739.8353624343872,
          615.3336334228516
        ]
      ],
      "group_id": null,
      "description": null,
      "difficult": false,
      "shape_type": "rectangle",
      "flags": {},
      "attributes": {},
      "kie_linking": []
    },
    {
      "label": "old",
      "score": 0.4433836340904236,
      "points": [
        [
          987.6172399520874,
          481.3359785079956
        ],
        [
          1016.9833612442017,
          481.3359785079956
        ],
        [
          1016.9833612442017,
          507.4818515777588
        ],
        [
          987.6172399520874,
          507.4818515777588
        ]
      ],
      "group_id": null,
      "description": null,
      "difficult": false,
      "shape_type": "rectangle",
      "flags": {},
      "attributes": {},
      "kie_linking": []
    },
    {
      "label": "2",
      "score": 0.4411372244358063,
      "points": [
        [
          825.4756355285645,
          569.800306558609
        ],
        [
          849.6849250793457,
          569.800306558609
        ],
        [
          849.6849250793457,
          596.4223062992096
        ],
        [
          825.4756355285645,
          596.4223062992096
        ]
      ],
      "group_id": null,
      "description": null,
      "difficult": false,
      "shape_type": "rectangle",
      "flags": {},
      "attributes": {},
      "kie_linking": []
    },
    {
      "label": "old",
      "score": 0.4351137578487396,
      "points": [
        [
          964.1006326675415,
          876.1035251617432
        ],
        [
          989.1412591934204,
          876.1035251617432
        ],
        [
          989.1412591934204,
          900.5794811248779
        ],
        [
          964.1006326675415,
          900.5794811248779
        ]
      ],
      "group_id": null,
      "description": null,
      "difficult": false,
      "shape_type": "rectangle",
      "flags": {},
      "attributes": {},
      "kie_linking": []
    },
    {
      "label": "2+",
      "score": 0.43303388357162476,
      "points": [
        [
          355.9785223007202,
          483.08069229125977
        ],
        [
          383.45972299575806,
          483.08069229125977
        ],
        [
          383.45972299575806,
          511.3644790649414
        ],
        [
          355.9785223007202,
          511.3644790649414
        ]
      ],
      "group_id": null,
      "description": null,
      "difficult": false,
      "shape_type": "rectangle",
      "flags": {},
      "attributes": {},
      "kie_linking": []
    },
    {
      "label": "old",
      "score": 0.4284237325191498,
      "points": [
        [
          1068.5107326507568,
          925.1792359352112
        ],
        [
          1097.6858711242676,
          925.1792359352112
        ],
        [
          1097.6858711242676,
          949.5602917671204
        ],
        [
          1068.5107326507568,
          949.5602917671204
        ]
      ],
      "group_id": null,
      "description": null,
      "difficult": false,
      "shape_type": "rectangle",
      "flags": {},
      "attributes": {},
      "kie_linking": []
    },
    {
      "label": "3+",
      "score": 0.4269176423549652,
      "points": [
        [
          308.6056184768677,
          270.2314496040344
        ],
        [
          331.1532688140869,
          270.2314496040344
        ],
        [
          331.1532688140869,
          298.1320881843567
        ],
        [
          308.6056184768677,
          298.1320881843567
        ]
      ],
      "group_id": null,
      "description": null,
      "difficult": false,
      "shape_type": "rectangle",
      "flags": {},
      "attributes": {},
      "kie_linking": []
    },
    {
      "label": "2",
      "score": 0.42292681336402893,
      "points": [
        [
          830.9289932250977,
          732.0501518249512
        ],
        [
          859.6148490905762,
          732.0501518249512
        ],
        [
          859.6148490905762,
          761.3284683227539
        ],
        [
          830.9289932250977,
          761.3284683227539
        ]
      ],
      "group_id": null,
      "description": null,
      "difficult": false,
      "shape_type": "rectangle",
      "flags": {},
      "attributes": {},
      "kie_linking": []
    },
    {
      "label": "2",
      "score": 0.42129161953926086,
      "points": [
        [
          763.7392568588257,
          616.5606832504272
        ],
        [
          791.0471391677856,
          616.5606832504272
        ],
        [
          791.0471391677856,
          639.2777347564697
        ],
        [
          763.7392568588257,
          639.2777347564697
        ]
      ],
      "group_id": null,
      "description": null,
      "difficult": false,
      "shape_type": "rectangle",
      "flags": {},
      "attributes": {},
      "kie_linking": []
    },
    {
      "label": "2",
      "score": 0.41974204778671265,
      "points": [
        [
          677.3059320449829,
          447.31635093688965
        ],
        [
          705.3220176696777,
          447.31635093688965
        ],
        [
          705.3220176696777,
          472.81107902526855
        ],
        [
          677.3059320449829,
          472.81107902526855
        ]
      ],
      "group_id": null,
      "description": null,
      "difficult": false,
      "shape_type": "rectangle",
      "flags": {},
      "attributes": {},
      "kie_linking": []
    },
    {
      "label": "2",
      "score": 0.41715148091316223,
      "points": [
        [
          488.07976365089417,
          574.4823789596558
        ],
        [
          518.7376797199249,
          574.4823789596558
        ],
        [
          518.7376797199249,
          602.8168678283691
        ],
        [
          488.07976365089417,
          602.8168678283691
        ]
      ],
      "group_id": null,
      "description": null,
      "difficult": false,
      "shape_type": "rectangle",
      "flags": {},
      "attributes": {},
      "kie_linking": []
    },
    {
      "label": "2",
      "score": 0.4118189513683319,
      "points": [
        [
          224.0735113620758,
          591.8943727016449
        ],
        [
          249.09680604934692,
          591.8943727016449
        ],
        [
          249.09680604934692,
          614.0078032016754
        ],
        [
          224.0735113620758,
          614.0078032016754
        ]
      ],
      "group_id": null,
      "description": null,
      "difficult": false,
      "shape_type": "rectangle",
      "flags": {},
      "attributes": {},
      "kie_linking": []
    },
    {
      "label": "old",
      "score": 0.40673011541366577,
      "points": [
        [
          959.9078798294067,
          849.2521095275879
        ],
        [
          985.9297323226929,
          849.2521095275879
        ],
        [
          985.9297323226929,
          872.8922939300537
        ],
        [
          959.9078798294067,
          872.8922939300537
        ]
      ],
      "group_id": null,
      "description": null,
      "difficult": false,
      "shape_type": "rectangle",
      "flags": {},
      "attributes": {},
      "kie_linking": []
    },
    {
      "label": "2",
      "score": 0.4023900628089905,
      "points": [
        [
          665.8144426345825,
          483.74521493911743
        ],
        [
          691.3987493515015,
          483.74521493911743
        ],
        [
          691.3987493515015,
          508.5125231742859
        ],
        [
          665.8144426345825,
          508.5125231742859
        ]
      ],
      "group_id": null,
      "description": null,
      "difficult": false,
      "shape_type": "rectangle",
      "flags": {},
      "attributes": {},
      "kie_linking": []
    },
    {
      "label": "2",
      "score": 0.40090855956077576,
      "points": [
        [
          712.9606652259827,
          576.3017416000366
        ],
        [
          739.3805956840515,
          576.3017416000366
        ],
        [
          739.3805956840515,
          602.4372673034668
        ],
        [
          712.9606652259827,
          602.4372673034668
        ]
      ],
      "group_id": null,
      "description": null,
      "difficult": false,
      "shape_type": "rectangle",
      "flags": {},
      "attributes": {},
      "kie_linking": []
    },
    {
      "label": "2",
      "score": 0.4006664752960205,
      "points": [
        [
          757.5126552581787,
          744.2054986953735
        ],
        [
          781.1284494400024,
          744.2054986953735
        ],
        [
          781.1284494400024,
          768.9779806137085
        ],
        [
          757.5126552581787,
          768.9779806137085
        ]
      ],
      "group_id": null,
      "description": null,
      "difficult": false,
      "shape_type": "rectangle",
      "flags": {},
      "attributes": {},
      "kie_linking": []
    },
    {
      "label": "2",
      "score": 0.40027880668640137,
      "points": [
        [
          551.5038347244263,
          596.9231557846069
        ],
        [
          577.1944236755371,
          596.9231557846069
        ],
        [
          577.1944236755371,
          621.8892812728882
        ],
        [
          551.5038347244263,
          621.8892812728882
        ]
      ],
      "group_id": null,
      "description": null,
      "difficult": false,
      "shape_type": "rectangle",
      "flags": {},
      "attributes": {},
      "kie_linking": []
    },
    {
      "label": "3",
      "score": 0.3960195779800415,
      "points": [
        [
          285.15275835990906,
          312.51766204833984
        ],
        [
          316.5954113006592,
          312.51766204833984
        ],
        [
          316.5954113006592,
          339.83478307724
        ],
        [
          285.15275835990906,
          339.83478307724
        ]
      ],
      "group_id": null,
      "description": null,
      "difficult": false,
      "shape_type": "rectangle",
      "flags": {},
      "attributes": {},
      "kie_linking": []
    },
    {
      "label": "2",
      "score": 0.3912787437438965,
      "points": [
        [
          794.476625919342,
          635.8079671859741
        ],
        [
          820.5021739006042,
          635.8079671859741
        ],
        [
          820.5021739006042,
          661.5105295181274
        ],
        [
          794.476625919342,
          661.5105295181274
        ]
      ],
      "group_id": null,
      "description": null,
      "difficult": false,
      "shape_type": "rectangle",
      "flags": {},
      "attributes": {},
      "kie_linking": []
    },
    {
      "label": "3",
      "score": 0.3912167251110077,
      "points": [
        [
          308.8463056087494,
          335.26490569114685
        ],
        [
          337.8562557697296,
          335.26490569114685
        ],
        [
          337.8562557697296,
          365.12112259864807
        ],
        [
          308.8463056087494,
          365.12112259864807
        ]
      ],
      "group_id": null,
      "description": null,
      "difficult": false,
      "shape_type": "rectangle",
      "flags": {},
      "attributes": {},
      "kie_linking": []
    },
    {
      "label": "2",
      "score": 0.38975271582603455,
      "points": [
        [
          389.76969480514526,
          564.1770672798157
        ],
        [
          416.37898206710815,
          564.1770672798157
        ],
        [
          416.37898206710815,
          593.4567141532898
        ],
        [
          389.76969480514526,
          593.4567141532898
        ]
      ],
      "group_id": null,
      "description": null,
      "difficult": false,
      "shape_type": "rectangle",
      "flags": {},
      "attributes": {},
      "kie_linking": []
    },
    {
      "label": "old",
      "score": 0.386494904756546,
      "points": [
        [
          97.69390165805817,
          416.18552327156067
        ],
        [
          125.73437750339508,
          416.18552327156067
        ],
        [
          125.73437750339508,
          444.033020734787
        ],
        [
          97.69390165805817,
          444.033020734787
        ]
      ],
      "group_id": null,
      "description": null,
      "difficult": false,
      "shape_type": "rectangle",
      "flags": {},
      "attributes": {},
      "kie_linking": []
    },
    {
      "label": "2",
      "score": 0.3853555917739868,
      "points": [
        [
          680.4051160812378,
          597.1566367149353
        ],
        [
          704.5313310623169,
          597.1566367149353
        ],
        [
          704.5313310623169,
          623.211452960968
        ],
        [
          680.4051160812378,
          623.211452960968
        ]
      ],
      "group_id": null,
      "description": null,
      "difficult": false,
      "shape_type": "rectangle",
      "flags": {},
      "attributes": {},
      "kie_linking": []
    },
    {
      "label": "2",
      "score": 0.37937772274017334,
      "points": [
        [
          378.713903427124,
          598.4046769142151
        ],
        [
          409.50581789016724,
          598.4046769142151
        ],
        [
          409.50581789016724,
          622.8911280632019
        ],
        [
          378.713903427124,
          622.8911280632019
        ]
      ],
      "group_id": null,
      "description": null,
      "difficult": false,
      "shape_type": "rectangle",
      "flags": {},
      "attributes": {},
      "kie_linking": []
    },
    {
      "label": "2",
      "score": 0.3792252540588379,
      "points": [
        [
          834.1253685951233,
          685.5011940002441
        ],
        [
          855.2304482460022,
          685.5011940002441
        ],
        [
          855.2304482460022,
          704.9323654174805
        ],
        [
          834.1253685951233,
          704.9323654174805
        ]
      ],
      "group_id": null,
      "description": null,
      "difficult": false,
      "shape_type": "rectangle",
      "flags": {},
      "attributes": {},
      "kie_linking": []
    },
    {
      "label": "2",
      "score": 0.37254804372787476,
      "points": [
        [
          740.5301141738892,
          548.9013981819153
        ],
        [
          767.8462743759155,
          548.9013981819153
        ],
        [
          767.8462743759155,
          574.6420979499817
        ],
        [
          740.5301141738892,
          574.6420979499817
        ]
      ],
      "group_id": null,
      "description": null,
      "difficult": false,
      "shape_type": "rectangle",
      "flags": {},
      "attributes": {},
      "kie_linking": []
    },
    {
      "label": "old",
      "score": 0.36311662197113037,
      "points": [
        [
          913.2756996154785,
          1180.9477281570435
        ],
        [
          939.3679141998291,
          1180.9477281570435
        ],
        [
          939.3679141998291,
          1204.4502925872803
        ],
        [
          913.2756996154785,
          1204.4502925872803
        ]
      ],
      "group_id": null,
      "description": null,
      "difficult": false,
      "shape_type": "rectangle",
      "flags": {},
      "attributes": {},
      "kie_linking": []
    },
    {
      "label": "2",
      "score": 0.35900062322616577,
      "points": [
        [
          774.7738361358643,
          663.9952278137207
        ],
        [
          801.688814163208,
          663.9952278137207
        ],
        [
          801.688814163208,
          689.374508857727
        ],
        [
          774.7738361358643,
          689.374508857727
        ]
      ],
      "group_id": null,
      "description": null,
      "difficult": false,
      "shape_type": "rectangle",
      "flags": {},
      "attributes": {},
      "kie_linking": []
    },
    {
      "label": "2+",
      "score": 0.3581653833389282,
      "points": [
        [
          498.4534418582916,
          528.5360813140869
        ],
        [
          527.7024900913239,
          528.5360813140869
        ],
        [
          527.7024900913239,
          554.4290351867676
        ],
        [
          498.4534418582916,
          554.4290351867676
        ]
      ],
      "group_id": null,
      "description": null,
      "difficult": false,
      "shape_type": "rectangle",
      "flags": {},
      "attributes": {},
      "kie_linking": []
    },
    {
      "label": "old",
      "score": 0.35287028551101685,
      "points": [
        [
          1103.8220071792603,
          712.8251147270203
        ],
        [
          1130.2066087722778,
          712.8251147270203
        ],
        [
          1130.2066087722778,
          735.0802302360535
        ],
        [
          1103.8220071792603,
          735.0802302360535
        ]
      ],
      "group_id": null,
      "description": null,
      "difficult": false,
      "shape_type": "rectangle",
      "flags": {},
      "attributes": {},
      "kie_linking": []
    },
    {
      "label": "2+",
      "score": 0.3516843318939209,
      "points": [
        [
          418.08533668518066,
          498.4875512123108
        ],
        [
          443.08523893356323,
          498.4875512123108
        ],
        [
          443.08523893356323,
          527.0905542373657
        ],
        [
          418.08533668518066,
          527.0905542373657
        ]
      ],
      "group_id": null,
      "description": null,
      "difficult": false,
      "shape_type": "rectangle",
      "flags": {},
      "attributes": {},
      "kie_linking": []
    },
    {
      "label": "2",
      "score": 0.3448137044906616,
      "points": [
        [
          756.763505935669,
          705.8016920089722
        ],
        [
          775.5311155319214,
          705.8016920089722
        ],
        [
          775.5311155319214,
          723.4711503982544
        ],
        [
          756.763505935669,
          723.4711503982544
        ]
      ],
      "group_id": null,
      "description": null,
      "difficult": false,
      "shape_type": "rectangle",
      "flags": {},
      "attributes": {},
      "kie_linking": []
    },
    {
      "label": "old",
      "score": 0.34254857897758484,
      "points": [
        [
          832.8151702880859,
          343.4037375450134
        ],
        [
          859.7169923782349,
          343.4037375450134
        ],
        [
          859.7169923782349,
          373.1738495826721
        ],
        [
          832.8151702880859,
          373.1738495826721
        ]
      ],
      "group_id": null,
      "description": null,
      "difficult": false,
      "shape_type": "rectangle",
      "flags": {},
      "attributes": {},
      "kie_linking": []
    },
    {
      "label": "old",
      "score": 0.342230886220932,
      "points": [
        [
          931.1875820159912,
          911.120343208313
        ],
        [
          956.3015270233154,
          911.120343208313
        ],
        [
          956.3015270233154,
          933.9170694351196
        ],
        [
          931.1875820159912,
          933.9170694351196
        ]
      ],
      "group_id": null,
      "description": null,
      "difficult": false,
      "shape_type": "rectangle",
      "flags": {},
      "attributes": {},
      "kie_linking": []
    },
    {
      "label": "2",
      "score": 0.3407095670700073,
      "points": [
        [
          516.1724936962128,
          602.823224067688
        ],
        [
          541.8753516674042,
          602.823224067688
        ],
        [
          541.8753516674042,
          629.2858004570007
        ],
        [
          516.1724936962128,
          629.2858004570007
        ]
      ],
      "group_id": null,
      "description": null,
      "difficult": false,
      "shape_type": "rectangle",
      "flags": {},
      "attributes": {},
      "kie_linking": []
    },
    {
      "label": "2",
      "score": 0.3388836681842804,
      "points": [
        [
          781.9359874725342,
          704.6140360832214
        ],
        [
          803.2808303833008,
          704.6140360832214
        ],
        [
          803.2808303833008,
          724.1049265861511
        ],
        [
          781.9359874725342,
          724.1049265861511
        ]
      ],
      "group_id": null,
      "description": null,
      "difficult": false,
      "shape_type": "rectangle",
      "flags": {},
      "attributes": {},
      "kie_linking": []
    },
    {
      "label": "old",
      "score": 0.33881592750549316,
      "points": [
        [
          1148.5427331924438,
          639.7519397735596
        ],
        [
          1168.48210811615,
          639.7519397735596
        ],
        [
          1168.48210811615,
          659.4308567047119
        ],
        [
          1148.5427331924438,
          659.4308567047119
        ]
      ],
      "group_id": null,
      "description": null,
      "difficult": false,
      "shape_type": "rectangle",
      "flags": {},
      "attributes": {},
      "kie_linking": []
    },
    {
      "label": "old",
      "score": 0.33680933713912964,
      "points": [
        [
          1084.9819660186768,
          735.9837770462036
        ],
        [
          1112.063388824463,
          735.9837770462036
        ],
        [
          1112.063388824463,
          759.144434928894
        ],
        [
          1084.9819660186768,
          759.144434928894
        ]
      ],
      "group_id": null,
      "description": null,
      "difficult": false,
      "shape_type": "rectangle",
      "flags": {},
      "attributes": {},
      "kie_linking": []
    },
    {
      "label": "2+",
      "score": 0.33667558431625366,
      "points": [
        [
          868.0577087402344,
          442.46668815612793
        ],
        [
          899.7966289520264,
          442.46668815612793
        ],
        [
          899.7966289520264,
          477.3492121696472
        ],
        [
          868.0577087402344,
          477.3492121696472
        ]
      ],
      "group_id": null,
      "description": null,
      "difficult": false,
      "shape_type": "rectangle",
      "flags": {},
      "attributes": {},
      "kie_linking": []
    },
    {
      "label": "2+",
      "score": 0.33090412616729736,
      "points": [
        [
          519.0132522583008,
          467.49571084976196
        ],
        [
          549.0896463394165,
          467.49571084976196
        ],
        [
          549.0896463394165,
          496.0288691520691
        ],
        [
          519.0132522583008,
          496.0288691520691
        ]
      ],
      "group_id": null,
      "description": null,
      "difficult": false,
      "shape_type": "rectangle",
      "flags": {},
      "attributes": {},
      "kie_linking": []
    },
    {
      "label": "2",
      "score": 0.3270077109336853,
      "points": [
        [
          851.7622327804565,
          779.5178079605103
        ],
        [
          877.6418828964233,
          779.5178079605103
        ],
        [
          877.6418828964233,
          801.2709283828735
        ],
        [
          851.7622327804565,
          801.2709283828735
        ]
      ],
      "group_id": null,
      "description": null,
      "difficult": false,
      "shape_type": "rectangle",
      "flags": {},
      "attributes": {},
      "kie_linking": []
    },
    {
      "label": "2",
      "score": 0.3251797556877136,
      "points": [
        [
          704.2133712768555,
          659.4832587242126
        ],
        [
          723.9935445785522,
          659.4832587242126
        ],
        [
          723.9935445785522,
          679.4329810142517
        ],
        [
          704.2133712768555,
          679.4329810142517
        ]
      ],
      "group_id": null,
      "description": null,
      "difficult": false,
      "shape_type": "rectangle",
      "flags": {},
      "attributes": {},
      "kie_linking": []
    },
    {
      "label": "2",
      "score": 0.3245493471622467,
      "points": [
        [
          652.9253196716309,
          596.292040348053
        ],
        [
          675.1901912689209,
          596.292040348053
        ],
        [
          675.1901912689209,
          616.5232110023499
        ],
        [
          652.9253196716309,
          616.5232110023499
        ]
      ],
      "group_id": null,
      "description": null,
      "difficult": false,
      "shape_type": "rectangle",
      "flags": {},
      "attributes": {},
      "kie_linking": []
    },
    {
      "label": "2+",
      "score": 0.3244042992591858,
      "points": [
        [
          351.3624143600464,
          523.3365297317505
        ],
        [
          386.76053285598755,
          523.3365297317505
        ],
        [
          386.76053285598755,
          552.9840993881226
        ],
        [
          351.3624143600464,
          552.9840993881226
        ]
      ],
      "group_id": null,
      "description": null,
      "difficult": false,
      "shape_type": "rectangle",
      "flags": {},
      "attributes": {},
      "kie_linking": []
    },
    {
      "label": "old",
      "score": 0.3223441243171692,
      "points": [
        [
          760.7664585113525,
          217.15293407440186
        ],
        [
          784.5701313018799,
          217.15293407440186
        ],
        [
          784.5701313018799,
          243.57648611068726
        ],
        [
          760.7664585113525,
          243.57648611068726
        ]
      ],
      "group_id": null,
      "description": null,
      "difficult": false,
      "shape_type": "rectangle",
      "flags": {},
      "attributes": {},
      "kie_linking": []
    },
    {
      "label": "old",
      "score": 0.3178369998931885,
      "points": [
        [
          1060.5511689186096,
          968.8573169708252
        ],
        [
          1092.3540949821472,
          968.8573169708252
        ],
        [
          1092.3540949821472,
          994.7498273849487
        ],
        [
          1060.5511689186096,
          994.7498273849487
        ]
      ],
      "group_id": null,
      "description": null,
      "difficult": false,
      "shape_type": "rectangle",
      "flags": {},
      "attributes": {},
      "kie_linking": []
    },
    {
      "label": "2+",
      "score": 0.31740063428878784,
      "points": [
        [
          674.6817660331726,
          397.920241355896
        ],
        [
          700.869472026825,
          397.920241355896
        ],
        [
          700.869472026825,
          431.28658056259155
        ],
        [
          674.6817660331726,
          431.28658056259155
        ]
      ],
      "group_id": null,
      "description": null,
      "difficult": false,
      "shape_type": "rectangle",
      "flags": {},
      "attributes": {},
      "kie_linking": []
    },
    {
      "label": "2",
      "score": 0.3169749975204468,
      "points": [
        [
          744.2159938812256,
          506.07091426849365
        ],
        [
          782.9182481765747,
          506.07091426849365
        ],
        [
          782.9182481765747,
          535.0778341293335
        ],
        [
          744.2159938812256,
          535.0778341293335
        ]
      ],
      "group_id": null,
      "description": null,
      "difficult": false,
      "shape_type": "rectangle",
      "flags": {},
      "attributes": {},
      "kie_linking": []
    },
    {
      "label": "old",
      "score": 0.3159763813018799,
      "points": [
        [
          1156.404070854187,
          902.3471808433533
        ],
        [
          1191.1765432357788,
          902.3471808433533
        ],
        [
          1191.1765432357788,
          928.0383610725403
        ],
        [
          1156.404070854187,
          928.0383610725403
        ]
      ],
      "group_id": null,
      "description": null,
      "difficult": false,
      "shape_type": "rectangle",
      "flags": {},
      "attributes": {},
      "kie_linking": []
    },
    {
      "label": "old",
      "score": 0.3153516352176666,
      "points": [
        [
          1019.1809940338135,
          489.35001373291016
        ],
        [
          1046.7922019958496,
          489.35001373291016
        ],
        [
          1046.7922019958496,
          519.6111822128296
        ],
        [
          1019.1809940338135,
          519.6111822128296
        ]
      ],
      "group_id": null,
      "description": null,
      "difficult": false,
      "shape_type": "rectangle",
      "flags": {},
      "attributes": {},
      "kie_linking": []
    },
    {
      "label": "2",
      "score": 0.3143041133880615,
      "points": [
        [
          845.1201844215393,
          536.3569903373718
        ],
        [
          872.4160933494568,
          536.3569903373718
        ],
        [
          872.4160933494568,
          563.4322047233582
        ],
        [
          845.1201844215393,
          563.4322047233582
        ]
      ],
      "group_id": null,
      "description": null,
      "difficult": false,
      "shape_type": "rectangle",
      "flags": {},
      "attributes": {},
      "kie_linking": []
    },
    {
      "label": "old",
      "score": 0.3138771951198578,
      "points": [
        [
          677.4309873580933,
          202.99529790878296
        ],
        [
          705.9979963302612,
          202.99529790878296
        ],
        [
          705.9979963302612,
          237.61562705039978
        ],
        [
          677.4309873580933,
          237.61562705039978
        ]
      ],
      "group_id": null,
      "description": null,
      "difficult": false,
      "shape_type": "rectangle",
      "flags": {},
      "attributes": {},
      "kie_linking": []
    },
    {
      "label": "2",
      "score": 0.312377393245697,
      "points": [
        [
          914.2671990394592,
          720.4324245452881
        ],
        [
          939.5115208625793,
          720.4324245452881
        ],
        [
          939.5115208625793,
          745.5265617370605
        ],
        [
          914.2671990394592,
          745.5265617370605
        ]
      ],
      "group_id": null,
      "description": null,
      "difficult": false,
      "shape_type": "rectangle",
      "flags": {},
      "attributes": {},
      "kie_linking": []
    },
    {
      "label": "2",
      "score": 0.30879998207092285,
      "points": [
        [
          756.3701581954956,
          712.396068572998
        ],
        [
          777.346043586731,
          712.396068572998
        ],
        [
          777.346043586731,
          737.0641899108887
        ],
        [
          756.3701581954956,
          737.0641899108887
        ]
      ],
      "group_id": null,
      "description": null,
      "difficult": false,
      "shape_type": "rectangle",
      "flags": {},
      "attributes": {},
      "kie_linking": []
    },
    {
      "label": "old",
      "score": 0.30803340673446655,
      "points": [
        [
          980.8159160614014,
          972.4896860122681
        ],
        [
          1005.2853679656982,
          972.4896860122681
        ],
        [
          1005.2853679656982,
          995.6429529190063
        ],
        [
          980.8159160614014,
          995.6429529190063
        ]
      ],
      "group_id": null,
      "description": null,
      "difficult": false,
      "shape_type": "rectangle",
      "flags": {},
      "attributes": {},
      "kie_linking": []
    },
    {
      "label": "old",
      "score": 0.3063678443431854,
      "points": [
        [
          904.2179846763611,
          886.4245057106018
        ],
        [
          928.9922404289246,
          886.4245057106018
        ],
        [
          928.9922404289246,
          913.7137627601624
        ],
        [
          904.2179846763611,
          913.7137627601624
        ]
      ],
      "group_id": null,
      "description": null,
      "difficult": false,
      "shape_type": "rectangle",
      "flags": {},
      "attributes": {},
      "kie_linking": []
    },
    {
      "label": "old",
      "score": 0.30571362376213074,
      "points": [
        [
          849.3393230438232,
          1202.6034355163574
        ],
        [
          869.2417430877686,
          1202.6034355163574
        ],
        [
          869.2417430877686,
          1226.1229991912842
        ],
        [
          849.3393230438232,
          1226.1229991912842
        ]
      ],
      "group_id": null,
      "description": null,
      "difficult": false,
      "shape_type": "rectangle",
      "flags": {},
      "attributes": {},
      "kie_linking": []
    },
    {
      "label": "2+",
      "score": 0.3053106665611267,
      "points": [
        [
          466.40857219696045,
          459.6087634563446
        ],
        [
          495.5630159378052,
          459.6087634563446
        ],
        [
          495.5630159378052,
          488.44258666038513
        ],
        [
          466.40857219696045,
          488.44258666038513
        ]
      ],
      "group_id": null,
      "description": null,
      "difficult": false,
      "shape_type": "rectangle",
      "flags": {},
      "attributes": {},
      "kie_linking": []
    },
    {
      "label": "2",
      "score": 0.3046720623970032,
      "points": [
        [
          614.5201826095581,
          582.6520681381226
        ],
        [
          637.6565980911255,
          582.6520681381226
        ],
        [
          637.6565980911255,
          606.1537456512451
        ],
        [
          614.5201826095581,
          606.1537456512451
        ]
      ],
      "group_id": null,
      "description": null,
      "difficult": false,
      "shape_type": "rectangle",
      "flags": {},
      "attributes": {},
      "kie_linking": []
    },
    {
      "label": "2",
      "score": 0.30143848061561584,
      "points": [
        [
          584.4359540939331,
          555.5181694030762
        ],
        [
          612.1532964706421,
          555.5181694030762
        ],
        [
          612.1532964706421,
          582.6563549041748
        ],
        [
          584.4359540939331,
          582.6563549041748
        ]
      ],
      "group_id": null,
      "description": null,
      "difficult": false,
      "shape_type": "rectangle",
      "flags": {},
      "attributes": {},
      "kie_linking": []
    },
    {
      "label": "old",
      "score": 0.29494577646255493,
      "points": [
        [
          1191.745204925537,
          693.9465665817261
        ],
        [
          1217.8238201141357,
          693.9465665817261
        ],
        [
          1217.8238201141357,
          719.6568155288696
        ],
        [
          1191.745204925537,
          719.6568155288696
        ]
      ],
      "group_id": null,
      "description": null,
      "difficult": false,
      "shape_type": "rectangle",
      "flags": {},
      "attributes": {},
      "kie_linking": []
    },
    {
      "label": "2",
      "score": 0.2946290373802185,
      "points": [
        [
          594.5438528060913,
          528.6943221092224
        ],
        [
          618.6974143981934,
          528.6943221092224
        ],
        [
          618.6974143981934,
          556.6723442077637
        ],
        [
          594.5438528060913,
          556.6723442077637
        ]
      ],
      "group_id": null,
      "description": null,
      "difficult": false,
      "shape_type": "rectangle",
      "flags": {},
      "attributes": {},
      "kie_linking": []
    },
    {
      "label": "3",
      "score": 0.29406827688217163,
      "points": [
        [
          355.5020999908447,
          280.64223051071167
        ],
        [
          380.35019159317017,
          280.64223051071167
        ],
        [
          380.35019159317017,
          307.01071977615356
        ],
        [
          355.5020999908447,
          307.01071977615356
        ]
      ],
      "group_id": null,
      "description": null,
      "difficult": false,
      "shape_type": "rectangle",
      "flags": {},
      "attributes": {},
      "kie_linking": []
    },
    {
      "label": "2",
      "score": 0.2925795912742615,
      "points": [
        [
          304.47262167930603,
          574.8075079917908
        ],
        [
          334.1982400417328,
          574.8075079917908
        ],
        [
          334.1982400417328,
          607.5179719924927
        ],
        [
          304.47262167930603,
          607.5179719924927
        ]
      ],
      "group_id": null,
      "description": null,
      "difficult": false,
      "shape_type": "rectangle",
      "flags": {},
      "attributes": {},
      "kie_linking": []
    },
    {
      "label": "old",
      "score": 0.2887973189353943,
      "points": [
        [
          817.9553174972534,
          309.2831861972809
        ],
        [
          842.5283908843994,
          309.2831861972809
        ],
        [
          842.5283908843994,
          337.2305357456207
        ],
        [
          817.9553174972534,
          337.2305357456207
        ]
      ],
      "group_id": null,
      "description": null,
      "difficult": false,
      "shape_type": "rectangle",
      "flags": {},
      "attributes": {},
      "kie_linking": []
    },
    {
      "label": "2",
      "score": 0.2873438596725464,
      "points": [
        [
          558.5344636440277,
          447.9628396034241
        ],
        [
          588.8552033901215,
          447.9628396034241
        ],
        [
          588.8552033901215,
          474.2433762550354
        ],
        [
          558.5344636440277,
          474.2433762550354
        ]
      ],
      "group_id": null,
      "description": null,
      "difficult": false,
      "shape_type": "rectangle",
      "flags": {},
      "attributes": {},
      "kie_linking": []
    },
    {
      "label": "2",
      "score": 0.2844088673591614,
      "points": [
        [
          761.9871520996094,
          582.2234654426575
        ],
        [
          782.0637035369873,
          582.2234654426575
        ],
        [
          782.0637035369873,
          604.3579602241516
        ],
        [
          761.9871520996094,
          604.3579602241516
        ]
      ],
      "group_id": null,
      "description": null,
      "difficult": false,
      "shape_type": "rectangle",
      "flags": {},
      "attributes": {},
      "kie_linking": []
    },
    {
      "label": "old",
      "score": 0.28258514404296875,
      "points": [
        [
          1170.9913444519043,
          797.7124691009521
        ],
        [
          1193.991026878357,
          797.7124691009521
        ],
        [
          1193.991026878357,
          819.8046875
        ],
        [
          1170.9913444519043,
          819.8046875
        ]
      ],
      "group_id": null,
      "description": null,
      "difficult": false,
      "shape_type": "rectangle",
      "flags": {},
      "attributes": {},
      "kie_linking": []
    },
    {
      "label": "2",
      "score": 0.28246644139289856,
      "points": [
        [
          863.7297749519348,
          710.8745622634888
        ],
        [
          889.0178513526917,
          710.8745622634888
        ],
        [
          889.0178513526917,
          735.4681825637817
        ],
        [
          863.7297749519348,
          735.4681825637817
        ]
      ],
      "group_id": null,
      "description": null,
      "difficult": false,
      "shape_type": "rectangle",
      "flags": {},
      "attributes": {},
      "kie_linking": []
    },
    {
      "label": "old",
      "score": 0.2823789119720459,
      "points": [
        [
          916.1243295669556,
          1117.7310848236084
        ],
        [
          941.0022068023682,
          1117.7310848236084
        ],
        [
          941.0022068023682,
          1141.5842771530151
        ],
        [
          916.1243295669556,
          1141.5842771530151
        ]
      ],
      "group_id": null,
      "description": null,
      "difficult": false,
      "shape_type": "rectangle",
      "flags": {},
      "attributes": {},
      "kie_linking": []
    },
    {
      "label": "3",
      "score": 0.2779664695262909,
      "points": [
        [
          341.96637749671936,
          315.37915229797363
        ],
        [
          369.9815022945404,
          315.37915229797363
        ],
        [
          369.9815022945404,
          343.8927984237671
        ],
        [
          341.96637749671936,
          343.8927984237671
        ]
      ],
      "group_id": null,
      "description": null,
      "difficult": false,
      "shape_type": "rectangle",
      "flags": {},
      "attributes": {},
      "kie_linking": []
    },
    {
      "label": "old",
      "score": 0.27708810567855835,
      "points": [
        [
          1035.2179336547852,
          680.2379322052002
        ],
        [
          1064.180507659912,
          680.2379322052002
        ],
        [
          1064.180507659912,
          713.5871982574463
        ],
        [
          1035.2179336547852,
          713.5871982574463
        ]
      ],
      "group_id": null,
      "description": null,
      "difficult": false,
      "shape_type": "rectangle",
      "flags": {},
      "attributes": {},
      "kie_linking": []
    },
    {
      "label": "old",
      "score": 0.276816725730896,
      "points": [
        [
          1126.9201374053955,
          552.0222008228302
        ],
        [
          1152.9956483840942,
          552.0222008228302
        ],
        [
          1152.9956483840942,
          579.8281610012054
        ],
        [
          1126.9201374053955,
          579.8281610012054
        ]
      ],
      "group_id": null,
      "description": null,
      "difficult": false,
      "shape_type": "rectangle",
      "flags": {},
      "attributes": {},
      "kie_linking": []
    },
    {
      "label": "2",
      "score": 0.27642714977264404,
      "points": [
        [
          543.266259431839,
          629.6933388710022
        ],
        [
          566.2432515621185,
          629.6933388710022
        ],
        [
          566.2432515621185,
          649.4412875175476
        ],
        [
          543.266259431839,
          649.4412875175476
        ]
      ],
      "group_id": null,
      "description": null,
      "difficult": false,
      "shape_type": "rectangle",
      "flags": {},
      "attributes": {},
      "kie_linking": []
    },
    {
      "label": "old",
      "score": 0.2728023827075958,
      "points": [
        [
          1013.9141845703125,
          1027.1413707733154
        ],
        [
          1031.5759563446045,
          1027.1413707733154
        ],
        [
          1031.5759563446045,
          1046.4420175552368
        ],
        [
          1013.9141845703125,
          1046.4420175552368
        ]
      ],
      "group_id": null,
      "description": null,
      "difficult": false,
      "shape_type": "rectangle",
      "flags": {},
      "attributes": {},
      "kie_linking": []
    },
    {
      "label": "2",
      "score": 0.2711068391799927,
      "points": [
        [
          825.5168771743774,
          839.48397397995
        ],
        [
          849.5230627059937,
          839.48397397995
        ],
        [
          849.5230627059937,
          859.0657734870911
        ],
        [
          825.5168771743774,
          859.0657734870911
        ]
      ],
      "group_id": null,
      "description": null,
      "difficult": false,
      "shape_type": "rectangle",
      "flags": {},
      "attributes": {},
      "kie_linking": []
    },
    {
      "label": "2+",
      "score": 0.2707381844520569,
      "points": [
        [
          510.61126470565796,
          502.44874477386475
        ],
        [
          539.6742081642151,
          502.44874477386475
        ],
        [
          539.6742081642151,
          528.4627628326416
        ],
        [
          510.61126470565796,
          528.4627628326416
        ]
      ],
      "group_id": null,
      "description": null,
      "difficult": false,
      "shape_type": "rectangle",
      "flags": {},
      "attributes": {},
      "kie_linking": []
    },
    {
      "label": "3",
      "score": 0.2641547918319702,
      "points": [
        [
          362.0008373260498,
          151.833798289299
        ],
        [
          387.1641540527344,
          151.833798289299
        ],
        [
          387.1641540527344,
          179.3118578195572
        ],
        [
          362.0008373260498,
          179.3118578195572
        ]
      ],
      "group_id": null,
      "description": null,
      "difficult": false,
      "shape_type": "rectangle",
      "flags": {},
      "attributes": {},
      "kie_linking": []
    },
    {
      "label": "old",
      "score": 0.26184433698654175,
      "points": [
        [
          1059.3859815597534,
          486.35212302207947
        ],
        [
          1088.8543939590454,
          486.35212302207947
        ],
        [
          1088.8543939590454,
          516.8416726589203
        ],
        [
          1059.3859815597534,
          516.8416726589203
        ]
      ],
      "group_id": null,
      "description": null,
      "difficult": false,
      "shape_type": "rectangle",
      "flags": {},
      "attributes": {},
      "kie_linking": []
    },
    {
      "label": "old",
      "score": 0.2617951035499573,
      "points": [
        [
          821.8380928039551,
          1192.2168970108032
        ],
        [
          843.5909175872803,
          1192.2168970108032
        ],
        [
          843.5909175872803,
          1213.4634399414062
        ],
        [
          821.8380928039551,
          1213.4634399414062
        ]
      ],
      "group_id": null,
      "description": null,
      "difficult": false,
      "shape_type": "rectangle",
      "flags": {},
      "attributes": {},
      "kie_linking": []
    },
    {
      "label": "old",
      "score": 0.259522944688797,
      "points": [
        [
          1101.485424041748,
          521.9579648971558
        ],
        [
          1127.888650894165,
          521.9579648971558
        ],
        [
          1127.888650894165,
          546.9199514389038
        ],
        [
          1101.485424041748,
          546.9199514389038
        ]
      ],
      "group_id": null,
      "description": null,
      "difficult": false,
      "shape_type": "rectangle",
      "flags": {},
      "attributes": {},
      "kie_linking": []
    },
    {
      "label": "2+",
      "score": 0.2586970031261444,
      "points": [
        [
          982.503719329834,
          539.3673348426819
        ],
        [
          1010.5966711044312,
          539.3673348426819
        ],
        [
          1010.5966711044312,
          564.9569630622864
        ],
        [
          982.503719329834,
          564.9569630622864
        ]
      ],
      "group_id": null,
      "description": null,
      "difficult": false,
      "shape_type": "rectangle",
      "flags": {},
      "attributes": {},
      "kie_linking": []
    },
    {
      "label": "2+",
      "score": 0.2566526532173157,
      "points": [
        [
          795.7537126541138,
          505.0634503364563
        ],
        [
          828.4206438064575,
          505.0634503364563
        ],
        [
          828.4206438064575,
          535.0548481941223
        ],
        [
          795.7537126541138,
          535.0548481941223
        ]
      ],
      "group_id": null,
      "description": null,
      "difficult": false,
      "shape_type": "rectangle",
      "flags": {},
      "attributes": {},
      "kie_linking": []
    },
    {
      "label": "old",
      "score": 0.2554107904434204,
      "points": [
        [
          1029.8418855667114,
          1139.9542713165283
        ],
        [
          1054.5703172683716,
          1139.9542713165283
        ],
        [
          1054.5703172683716,
          1164.109754562378
        ],
        [
          1029.8418855667114,
          1164.109754562378
        ]
      ],
      "group_id": null,
      "description": null,
      "difficult": false,
      "shape_type": "rectangle",
      "flags": {},
      "attributes": {},
      "kie_linking": []
    },
    {
      "label": "2+",
      "score": 0.2550913393497467,
      "points": [
        [
          608.6326050758362,
          451.41908168792725
        ],
        [
          633.463032245636,
          451.41908168792725
        ],
        [
          633.463032245636,
          476.0985851287842
        ],
        [
          608.6326050758362,
          476.0985851287842
        ]
      ],
      "group_id": null,
      "description": null,
      "difficult": false,
      "shape_type": "rectangle",
      "flags": {},
      "attributes": {},
      "kie_linking": []
    },
    {
      "label": "3",
      "score": 0.2543408274650574,
      "points": [
        [
          29.525634720921516,
          663.4531736373901
        ],
        [
          56.83274328708649,
          663.4531736373901
        ],
        [
          56.83274328708649,
          692.2368860244751
        ],
        [
          29.525634720921516,
          692.2368860244751
        ]
      ],
      "group_id": null,
      "description": null,
      "difficult": false,
      "shape_type": "rectangle",
      "flags": {},
      "attributes": {},
      "kie_linking": []
    },
    {
      "label": "2",
      "score": 0.25403863191604614,
      "points": [
        [
          377.97595143318176,
          629.6369457244873
        ],
        [
          401.294184923172,
          629.6369457244873
        ],
        [
          401.294184923172,
          654.4614601135254
        ],
        [
          377.97595143318176,
          654.4614601135254
        ]
      ],
      "group_id": null,
      "description": null,
      "difficult": false,
      "shape_type": "rectangle",
      "flags": {},
      "attributes": {},
      "kie_linking": []
    },
    {
      "label": "old",
      "score": 0.25349169969558716,
      "points": [
        [
          1095.0169897079468,
          563.507297039032
        ],
        [
          1121.517481803894,
          563.507297039032
        ],
        [
          1121.517481803894,
          587.3057961463928
        ],
        [
          1095.0169897079468,
          587.3057961463928
        ]
      ],
      "group_id": null,
      "description": null,
      "difficult": false,
      "shape_type": "rectangle",
      "flags": {},
      "attributes": {},
      "kie_linking": []
    },
    {
      "label": "old",
      "score": 0.2514943480491638,
      "points": [
        [
          1002.7165603637695,
          874.2572593688965
        ],
        [
          1028.5237789154053,
          874.2572593688965
        ],
        [
          1028.5237789154053,
          896.5537643432617
        ],
        [
          1002.7165603637695,
          896.5537643432617
        ]
      ],
      "group_id": null,
      "description": null,
      "difficult": false,
      "shape_type": "rectangle",
      "flags": {},
      "attributes": {},
      "kie_linking": []
    }
  ],
  "imagePath": "20250515082200863.bmp",
  "imageData": null,
  "imageHeight": 1240,
  "imageWidth": 1240,
  "description": ""
}